AUTHORS.txt
CHANGES.txt
LICENSE.txt
MANIFEST.in
README.rst
TODO.txt
dev_requirements.txt
setup.cfg
setup.py
tool_requirements.txt
docs/1to2.rst
docs/Makefile
docs/admin_client.rst
docs/architecture.rst
docs/client.rst
docs/conf.py
docs/index.rst
docs/job.rst
docs/library.rst
docs/types_of_jobs.rst
docs/worker.rst
gearman/__init__.py
gearman/admin_client.py
gearman/admin_client_handler.py
gearman/client.py
gearman/client_handler.py
gearman/command_handler.py
gearman/compat.py
gearman/connection.py
gearman/connection_manager.py
gearman/constants.py
gearman/errors.py
gearman/io.py
gearman/job.py
gearman/protocol.py
gearman/util.py
gearman/version.py
gearman/worker.py
gearman/worker_handler.py
gearman3.egg-info/PKG-INFO
gearman3.egg-info/SOURCES.txt
gearman3.egg-info/dependency_links.txt
gearman3.egg-info/top_level.txt