Metadata-Version: 1.1
Name: gearman3
Version: 0.2.0
Summary: A Python 3 fork of the Gearman API - Client, worker, and admin client interfaces
Home-page: https://github.com/wellcometrust/python-gearman
Author: Wellcome Digital Platform
Author-email: wellcomedigitalplatform@wellcome.ac.uk
License: Apache / MIT
Platform: UNKNOWN
Classifier: Development Status :: 5 - Production/Stable
Classifier: Intended Audience :: Developers
Classifier: License :: OSI Approved :: Apache Software License
Classifier: Natural Language :: English
Classifier: Operating System :: OS Independent
Classifier: Programming Language :: Python
Classifier: Programming Language :: Python :: 2.4
Classifier: Programming Language :: Python :: 2.5
Classifier: Programming Language :: Python :: 2.6
Classifier: Programming Language :: Python :: 2.7
Classifier: Topic :: Software Development :: Libraries :: Python Modules
